lamnet/__init__.py
lamnet/data.py
lamnet/layers.py
lamnet/loss.py
lamnet/nn.py
lamnet/optim.py
lamnet/tensor.py
lamnet/train.py
lamnet-0.1.0.dist-info/LICENSE.txt
lamnet-0.1.0.dist-info/METADATA
lamnet-0.1.0.dist-info/RECORD
lamnet-0.1.0.dist-info/WHEEL
lamnet-0.1.0.dist-info/top_level.txt
sample/__init__.py
